fustor_agent/__init__.py
fustor_agent/app.py
fustor_agent/cli.py
fustor_agent/api/__init__.py
fustor_agent/api/configs_api.py
fustor_agent/api/dependencies.py
fustor_agent/api/drivers_api.py
fustor_agent/api/logs_handlers.py
fustor_agent/api/metrics_api.py
fustor_agent/api/pushers_api.py
fustor_agent/api/routes.py
fustor_agent/api/schemas.py
fustor_agent/api/sources_api.py
fustor_agent/api/sync_instances_handlers.py
fustor_agent/api/syncs_api.py
fustor_agent/api/system_handlers.py
fustor_agent/runtime/__init__.py
fustor_agent/runtime/bus.py
fustor_agent/runtime/sync.py
fustor_agent/services/common.py
fustor_agent/services/log.py
fustor_agent/services/schema_cache.py
fustor_agent/services/configs/__init__.py
fustor_agent/services/configs/base.py
fustor_agent/services/configs/pusher.py
fustor_agent/services/configs/source.py
fustor_agent/services/configs/sync.py
fustor_agent/services/drivers/pusher_driver.py
fustor_agent/services/drivers/source_driver.py
fustor_agent/services/instances/base.py
fustor_agent/services/instances/bus.py
fustor_agent/services/instances/sync.py
fustor_agent-0.2.16.dist-info/METADATA
fustor_agent-0.2.16.dist-info/WHEEL
fustor_agent-0.2.16.dist-info/entry_points.txt
fustor_agent-0.2.16.dist-info/top_level.txt
fustor_agent-0.2.16.dist-info/RECORD
