Metadata-Version: 2.4
Name: fustor-agent
Version: 0.2.16
Summary: realtime data sync agent for various data sources
Author-email: Huajin Wang <wanghuajin999@163.com>
Requires-Python: >=3.11
Requires-Dist: click>=8.1.7
Requires-Dist: fastapi>=0.115.13
Requires-Dist: uvicorn[standard]>=0.34.3
Requires-Dist: pydantic>=2.11.7
Requires-Dist: fustor-core
Requires-Dist: fustor-source-fs
Requires-Dist: fustor-pusher-echo
Requires-Dist: fustor-agent-sdk
Requires-Dist: fustor-pusher-fusion
Provides-Extra: dev
Requires-Dist: pytest>=8.0.0; extra == "dev"
Requires-Dist: ruff>=0.1.0; extra == "dev"
Requires-Dist: mypy>=1.0.0; extra == "dev"
Requires-Dist: pytest-asyncio>=0.23.0; extra == "dev"
Requires-Dist: pytest-mock>=3.0.0; extra == "dev"
